wuy.py
wuy-0.10.1.dist-info/LICENSE
wuy-0.10.1.dist-info/WHEEL
wuy-0.10.1.dist-info/METADATA
wuy-0.10.1.dist-info/RECORD
