Metadata-Version: 2.1
Name: wuy
Version: 0.10.1
Summary: A simple module for making HTML GUI applications with python3/asyncio
Home-page: https://github.com/manatlan/wuy
License: GPL-2.0
Keywords: gui,html,javascript,electron,asyncio,aiohttp,websocket
Author: manatlan
Author-email: manatlan@gmail.com
Requires-Python: >=3.5,<4.0
Classifier: License :: OSI Approved :: GNU General Public License v2 (GPLv2)
Classifier: Operating System :: OS Independent
Classifier: Programming Language :: Python :: 3
Classifier: Programming Language :: Python :: 3.5
Classifier: Programming Language :: Python :: 3.6
Classifier: Programming Language :: Python :: 3.7
Classifier: Topic :: Software Development :: Libraries :: Python Modules
Requires-Dist: aiohttp (>=3.0.0b0,<4.0)
Project-URL: Documentation, https://github.com/manatlan/wuy
Project-URL: Repository, https://github.com/manatlan/wuy
